talos_sdk/__init__.py
talos_sdk/canonical.py
talos_sdk/client.py
talos_sdk/container.py
talos_sdk/crypto.py
talos_sdk/errors.py
talos_sdk/frames.py
talos_sdk/mcp.py
talos_sdk/mcp_client.py
talos_sdk/py.typed
talos_sdk/security.py
talos_sdk/session.py
talos_sdk/validation.py
talos_sdk/wallet.py
talos_sdk/a2a/__init__.py
talos_sdk/a2a/errors.py
talos_sdk/a2a/models.py
talos_sdk/a2a/ratchet_crypto.py
talos_sdk/a2a/sequence_tracker.py
talos_sdk/a2a/session_client.py
talos_sdk/a2a/transport.py
talos_sdk/adapters/crypto.py
talos_sdk/adapters/hash.py
talos_sdk/adapters/memory_store.py
talos_sdk/conformance/__init__.py
talos_sdk/conformance/cli.py
talos_sdk/conformance/handlers.py
talos_sdk/conformance/reports.py
talos_sdk/conformance/runner.py
talos_sdk/ports/__init__.py
talos_sdk/ports/audit_store.py
talos_sdk/ports/crypto.py
talos_sdk/ports/hash.py
talos_sdk/ports/key_value_store.py
talos_sdk/secrets/__init__.py
talos_sdk/secrets/kek.py
talos_sdk/secrets/local_provider.py
talos_sdk_py-0.1.25.dist-info/licenses/LICENSE
talos_sdk_py-0.1.25.dist-info/licenses/NOTICE
talos_sdk_py-0.1.25.dist-info/METADATA
talos_sdk_py-0.1.25.dist-info/WHEEL
talos_sdk_py-0.1.25.dist-info/entry_points.txt
talos_sdk_py-0.1.25.dist-info/top_level.txt
talos_sdk_py-0.1.25.dist-info/RECORD
