Metadata-Version: 2.4
Name: talos-sdk-py
Version: 0.1.25
Summary: Talos Protocol Python SDK
Author-email: Talos Team <sdk@talosprotocol.com>
License:                                  Apache License
Keywords: blockchain,security,mcp
Classifier: Development Status :: 4 - Beta
Classifier: Intended Audience :: Developers
Classifier: License :: OSI Approved :: Apache Software License
Classifier: Programming Language :: Python :: 3
Requires-Python: >=3.10
License-File: LICENSE
License-File: NOTICE
Requires-Dist: pydantic>=2.0.0
Requires-Dist: cryptography>=41.0.0
Requires-Dist: jsonschema>=4.18.0
Requires-Dist: requests>=2.31.0
Provides-Extra: dev
Requires-Dist: pytest; extra == "dev"
Requires-Dist: pytest-asyncio; extra == "dev"
Requires-Dist: ruff; extra == "dev"
Requires-Dist: mypy; extra == "dev"
Requires-Dist: build; extra == "dev"
Requires-Dist: types-requests; extra == "dev"
Requires-Dist: types-setuptools; extra == "dev"
Dynamic: license-file
